makey/__init__.py
makey/makey.py
makey_cli-1.3.1.dist-info/entry_points.txt
makey_cli-1.3.1.dist-info/LICENSE
makey_cli-1.3.1.dist-info/WHEEL
makey_cli-1.3.1.dist-info/METADATA
makey_cli-1.3.1.dist-info/RECORD
