Metadata-Version: 2.1
Name: makey-cli
Version: 1.3.1
Summary: A simple and lightweight tool for making secure passkeys in your terminal.
Author-email: Bradley Wojcik <bradleycwojcik@gmail.com>
Requires-Python: >=3.8
Classifier: License :: OSI Approved :: MIT License
Requires-Dist: click>=8
Requires-Dist: pyperclip>=1.8
Requires-Dist: black ; extra == "dev"
Requires-Dist: flake8 ; extra == "dev"
Requires-Dist: flit ; extra == "dev"
Requires-Dist: isort ; extra == "dev"
Requires-Dist: pre-commit ; extra == "dev"
Requires-Dist: homebrew-pypi-poet ; extra == "dev"
Requires-Dist: pytest >=6 ; extra == "test"
Requires-Dist: pytest-cov ; extra == "test"
Requires-Dist: pytest-mock ; extra == "test"
Project-URL: Home, https://boldandbrad.github.io/makey-cli
Project-URL: Issues, https://github.com/boldandbrad/makey-cli/issues
Project-URL: Source, https://github.com/boldandbrad/makey-cli
Provides-Extra: dev
Provides-Extra: test
